donguk777_lotto/__init__.py
donguk777_lotto/draw.py
DONGUK777_lotto-0.2.0.dist-info/METADATA
DONGUK777_lotto-0.2.0.dist-info/WHEEL
DONGUK777_lotto-0.2.0.dist-info/top_level.txt
DONGUK777_lotto-0.2.0.dist-info/RECORD
