Metadata-Version: 2.1
Name: DONGUK777_lotto
Version: 0.2.0
Summary: Default template for PDM package
Author-email: DONGUK777 <kimdongyork@gmail.com>
License: MIT
Requires-Python: >=3.9
